LICENSE
MANIFEST.in
README.md
requirements.txt
setup.py
leetcode_alg/__init__.py
leetcode_alg/_types.py
leetcode_alg/ext.py
leetcode_alg.egg-info/PKG-INFO
leetcode_alg.egg-info/SOURCES.txt
leetcode_alg.egg-info/dependency_links.txt
leetcode_alg.egg-info/requires.txt
leetcode_alg.egg-info/top_level.txt
leetcode_alg/_alg/__init__.py
leetcode_alg/_alg/_array.py
leetcode_alg/_alg/_date.py
leetcode_alg/_alg/_dp.py
leetcode_alg/_alg/_graph.py
leetcode_alg/_alg/_greed.py
leetcode_alg/_alg/_knapsack.py
leetcode_alg/_alg/_linked_list.py
leetcode_alg/_alg/_math.py
leetcode_alg/_alg/_monotone_deque.py
leetcode_alg/_alg/_monotone_stack.py
leetcode_alg/_alg/_search.py
leetcode_alg/_alg/_string.py
leetcode_alg/_alg/_string_op.py
leetcode_alg/_alg/_tree.py
leetcode_alg/_alg/_extension/__init__.py
leetcode_alg/_alg/_unimportant/__init__.py
leetcode_alg/_alg/_unimportant/_array.py
leetcode_alg/_alg/_unimportant/_bisect.py
leetcode_alg/_alg/_unimportant/_math.py
leetcode_alg/_alg/_unimportant/_random.py
leetcode_alg/_alg/_unimportant/_sort.py
leetcode_alg/_ds/__init__.py
leetcode_alg/_ds/_binary_indexed_tree.py
leetcode_alg/_ds/_heap.py
leetcode_alg/_ds/_linked_list.py
leetcode_alg/_ds/_segment_tree.py
leetcode_alg/_ds/_sorted_list.py
leetcode_alg/_ds/_string_hasher.py
leetcode_alg/_ds/_trie.py
leetcode_alg/_ds/_union_find.py
leetcode_alg/_ds/_extension/__init__.py
leetcode_alg/_ds/_extension/_bbst.py
leetcode_alg/_ds/_extension/_huffman.py
leetcode_alg/_ds/_extension/_rb_tree.py
leetcode_alg/_ds/_unimportant/__init__.py
leetcode_alg/_ds/_unimportant/_ordered_dict.py
leetcode_alg/_lc/__init__.py
leetcode_alg/_lc/_lc_ds.py
leetcode_alg/_lc/_lc_tools.py
tests/test_answer.py
tests/test_array.py
tests/test_bit_st.py
tests/test_dp.py
tests/test_heap.py
tests/test_ll.py
tests/test_math.py
tests/test_python.py
tests/test_search.py
tests/test_sl.py
tests/test_str.py
tests/test_tools.py
tests/test_unimp.py