Metadata-Version: 2.1
Name: leetcode-alg
Version: 0.1.0.1
Summary: `leetcode-alg`是针对leetcode解题的数据结构和算法库, 其设计准则是: 以通用性为核心, 并以最大可能进行性能优化. 
Home-page: https://github.com/Jintao-Huang/LeetCode-Py
Author: Jintao Huang
Author-email: huangjintao@mail.ustc.edu.cn
License: MIT
Classifier: License :: OSI Approved :: MIT License
Classifier: Operating System :: OS Independent
Classifier: Programming Language :: Python
Classifier: Programming Language :: Python :: 3
Classifier: Programming Language :: Python :: 3.8
Classifier: Programming Language :: Python :: 3.9
Classifier: Programming Language :: Python :: 3.10
Requires-Python: >=3.8
License-File: LICENSE
